awesomeyaml/__init__.py
awesomeyaml/_dist_info.py
awesomeyaml/builder.py
awesomeyaml/config.py
awesomeyaml/errors.py
awesomeyaml/eval_context.py
awesomeyaml/namespace.py
awesomeyaml/utils.py
awesomeyaml/version.py
awesomeyaml/yaml.py
awesomeyaml/nodes/__init__.py
awesomeyaml/nodes/append.py
awesomeyaml/nodes/bind.py
awesomeyaml/nodes/call.py
awesomeyaml/nodes/clear.py
awesomeyaml/nodes/composed.py
awesomeyaml/nodes/dict.py
awesomeyaml/nodes/eval.py
awesomeyaml/nodes/extend.py
awesomeyaml/nodes/fstr.py
awesomeyaml/nodes/function.py
awesomeyaml/nodes/import.py
awesomeyaml/nodes/include.py
awesomeyaml/nodes/list.py
awesomeyaml/nodes/node.py
awesomeyaml/nodes/node_path.py
awesomeyaml/nodes/path.py
awesomeyaml/nodes/prev.py
awesomeyaml/nodes/recurse.py
awesomeyaml/nodes/required.py
awesomeyaml/nodes/scalar.py
awesomeyaml/nodes/stream.py
awesomeyaml/nodes/tuple.py
awesomeyaml/nodes/xref.py
awesomeyaml-1.1.4.data/data/LICENSE
awesomeyaml-1.1.4.data/data/README.md
awesomeyaml-1.1.4.dist-info/LICENSE
awesomeyaml-1.1.4.dist-info/METADATA
awesomeyaml-1.1.4.dist-info/WHEEL
awesomeyaml-1.1.4.dist-info/top_level.txt
awesomeyaml-1.1.4.dist-info/RECORD
