Metadata-Version: 2.1
Name: awesomeyaml
Version: 1.1.4
Summary: Config-building utilities using YAML
Home-page: https://github.com/SamsungLabs/awesomeyaml
Download-URL: https://github.com/SamsungLabs/awesomeyaml
Author: Łukasz Dudziak
Author-email: l.dudziak@samsung.com
Requires-Python: >=3.6.0
License-File: LICENSE
Requires-Dist: pyyaml >=5.1
